datasette_simple_html/__init__.py
datasette_simple_html-0.2.dist-info/LICENSE
datasette_simple_html-0.2.dist-info/METADATA
datasette_simple_html-0.2.dist-info/WHEEL
datasette_simple_html-0.2.dist-info/entry_points.txt
datasette_simple_html-0.2.dist-info/top_level.txt
datasette_simple_html-0.2.dist-info/RECORD
