Metadata-Version: 2.1
Name: datasette-simple-html
Version: 0.2
Summary: Datasette SQL functions for very simple HTML operations
Home-page: https://github.com/simonw/datasette-simple-html
Author: Simon Willison
License: Apache License, Version 2.0
Project-URL: Issues, https://github.com/simonw/datasette-simple-html/issues
Project-URL: CI, https://github.com/simonw/datasette-simple-html/actions
Project-URL: Changelog, https://github.com/simonw/datasette-simple-html/releases
Classifier: Framework :: Datasette
Classifier: License :: OSI Approved :: Apache Software License
Requires-Python: >=3.7
License-File: LICENSE
Requires-Dist: datasette
Provides-Extra: test
Requires-Dist: pytest ; extra == 'test'
Requires-Dist: pytest-asyncio ; extra == 'test'
